common/__init__.py
common/base/__init__.py
common/base/executors/__init__.py
common/base/executors/batch_work_executor.py
common/base/executors/bounded_executor.py
common/base/executors/fail_safe_executor.py
common/base/executors/utils/__init__.py
common/base/executors/utils/atomic_counter.py
common/base/executors/utils/progress_logger.py
common/base/executors/utils/retriable_value_error.py
common/base/executors/utils/utils.py
common/base/jobs/__init__.py
common/base/jobs/base_job.py
common/base/jobs/job_run_multithread.py
common/base/jobs/utils/__init__.py
common/base/jobs/utils/job_utils.py
common/base/mappers/__init__.py
common/base/utils/__init__.py
common/jobs/__init__.py
common/server/__init__.py
common/server/state_querier_server.py
heath_check/__init__.py
heath_check/check_telnet.py
heath_check/health_check_job.py
heath_check/model.py
heath_check/check_rule/__init__.py
heath_check/check_rule/telnet_rule_check.py
helper/__init__.py
helper/helper.py
telnet/__init__.py
telnet/check_multithread.py
telnet/check_telnet.py
telnet/helper.py
telnet/separate_host_port_multithread.py
health_check_helper_thanhnv-1.1.6.dist-info/LICENSE
health_check_helper_thanhnv-1.1.6.dist-info/METADATA
health_check_helper_thanhnv-1.1.6.dist-info/WHEEL
health_check_helper_thanhnv-1.1.6.dist-info/top_level.txt
health_check_helper_thanhnv-1.1.6.dist-info/RECORD
