Metadata-Version: 2.1
Name: health-check-helper-thanhnv
Version: 1.1.6
Home-page: https://github.com/thanhnv2303/HelpTool
Author: LinLin
Author-email: nguyenthanh2303@gmail.com
Project-URL: Bug Tracker, https://github.com/thanhnv2303/HelpTool
Classifier: Development Status :: 5 - Production/Stable
Classifier: Intended Audience :: Developers
Classifier: License :: OSI Approved :: MIT License
Classifier: Programming Language :: Python :: 3
Classifier: Programming Language :: Python :: 3.7
Classifier: Programming Language :: Python :: 3.8
Classifier: Programming Language :: Python :: 3.9
License-File: LICENSE
Requires-Dist: requests (>=2.26.0)
Requires-Dist: sortedcontainers (>=2.4.0)
Requires-Dist: pyspnego (==0.9.2)
Requires-Dist: requests-kerberos (==0.14.0)
